DataReader/__init__.py
DataReader/module.py
DataReader/config/__init__.py
DataReader/config/config.py
DataReader/koroad/__init__.py
DataReader/koroad/bicycle.py
DataReader/koroad/city.py
yolov5/__init__.py
yolov5/detect.py
yolov5/export.py
yolov5/data/__init__.py
yolov5/data/scripts/__init__.py
yolov5/models/__init__.py
yolov5/models/common.py
yolov5/models/experimental.py
yolov5/models/tf.py
yolov5/models/yolo.py
yolov5/runs/__init__.py
yolov5/runs/detect/__init__.py
yolov5/test/__init__.py
yolov5/utils/__init__.py
yolov5/utils/activations.py
yolov5/utils/augmentations.py
yolov5/utils/autoanchor.py
yolov5/utils/autobatch.py
yolov5/utils/callbacks.py
yolov5/utils/dataloaders.py
yolov5/utils/downloads.py
yolov5/utils/general.py
yolov5/utils/loss.py
yolov5/utils/metrics.py
yolov5/utils/plots.py
yolov5/utils/torch_utils.py
yolov5/utils/aws/__init__.py
yolov5/utils/aws/resume.py
yolov5/utils/docker/__init__.py
yolov5/utils/flask_rest_api/__init__.py
yolov5/utils/flask_rest_api/example_request.py
yolov5/utils/flask_rest_api/restapi.py
yolov5/utils/google_app_engine/__init__.py
yolov5/utils/loggers/__init__.py
yolov5/utils/loggers/clearml/__init__.py
yolov5/utils/loggers/clearml/clearml_utils.py
yolov5/utils/loggers/clearml/hpo.py
yolov5/utils/loggers/comet/__init__.py
yolov5/utils/loggers/comet/comet_utils.py
yolov5/utils/loggers/comet/hpo.py
yolov5/utils/loggers/wandb/__init__.py
yolov5/utils/loggers/wandb/log_dataset.py
yolov5/utils/loggers/wandb/sweep.py
yolov5/utils/loggers/wandb/wandb_utils.py
yolov5/utils/segment/__init__.py
yolov5/utils/segment/augmentations.py
yolov5/utils/segment/dataloaders.py
yolov5/utils/segment/general.py
yolov5/utils/segment/loss.py
yolov5/utils/segment/metrics.py
yolov5/utils/segment/plots.py
kadap1-0.0.2.dist-info/LICENSE
kadap1-0.0.2.dist-info/METADATA
kadap1-0.0.2.dist-info/WHEEL
kadap1-0.0.2.dist-info/top_level.txt
kadap1-0.0.2.dist-info/RECORD
